alerthub/__init__.py
alerthub/core/__init__.py
alerthub/core/base_email_service.py
alerthub/core/email_service_manager.py
alerthub/core/services/__init__.py
alerthub/core/services/gmail_service.py
alerthub/core/services/outlook_service.py
alerthub/core/services/sendgrid_service.py
alerthub/core/services/smtp_service.py
alerthub/utils/__init__.py
alerthub/utils/constants.py
alerthub/utils/generate_gmail_refresh_token.py
alerthub-0.1.1.dist-info/LICENSE
alerthub-0.1.1.dist-info/METADATA
alerthub-0.1.1.dist-info/WHEEL
alerthub-0.1.1.dist-info/top_level.txt
alerthub-0.1.1.dist-info/RECORD
