Metadata-Version: 2.1
Name: alerthub
Version: 0.1.1
Summary: A Python package for managing email services across multiple platforms
Home-page: https://github.com/akvdkharnath/alerthub
Author: Harnath Atmakuri
Author-email: akvdkharnath@gmail.com
License: UNKNOWN
Platform: UNKNOWN
Classifier: Development Status :: 4 - Beta
Classifier: Intended Audience :: Developers
Classifier: License :: OSI Approved :: MIT License
Classifier: Programming Language :: Python :: 3
Classifier: Programming Language :: Python :: 3.6
Classifier: Programming Language :: Python :: 3.7
Classifier: Programming Language :: Python :: 3.8
Classifier: Programming Language :: Python :: 3.9
Requires-Python: >=3.6
Requires-Dist: google-api-python-client
Requires-Dist: google-auth
Requires-Dist: google-auth-httplib2
Requires-Dist: google-auth-oauthlib
Requires-Dist: python-dotenv
Requires-Dist: requests
